ed_analytics/__init__.py
ed_analytics/consts.py
ed_analytics/utils.py
ed_analytics/github/__init__.py
ed_analytics/github/abc.py
ed_analytics.py-1.0.0.dist-info/LICENSE
ed_analytics.py-1.0.0.dist-info/METADATA
ed_analytics.py-1.0.0.dist-info/WHEEL
ed_analytics.py-1.0.0.dist-info/top_level.txt
ed_analytics.py-1.0.0.dist-info/RECORD
